<?xml version="1.0" ?>
<img id="0" stype="smenu" id1="1" id2="40" wcount="3" wcounta="" wcountb="" qtext="Okay dude, be smart... If I'm not helping the account, she'll report my overdue projects to the boss. If I'm not helping the secretary, she'll start rumors for sure! Here comes trouble..." ctext1="I'm gonna help Bridgette, the account." ctext2="I'm gonna help Rachel, the secretary." photo1="1" photo2="2" video="Game_DisplayPlayer_Work_sucks_Scene0.mp4" />
<img id="1" stype="smenu" id1="2" id2="4" wcount="3" wcounta="" wcountb="" qtext="Gosh... I have no clue what she's talking about... Hello ladies! I must not stare at those jugs!" ctext1="Okay, I'm lost. I want to touch them!" ctext2="Concentrate! Don't touch her boobs... will wank in the loo afterwards!" photo1="1-a" photo2="1-b" video="Game_DisplayPlayer_Work_sucks_Scene1.mp4" />
<img id="2" type="auto" id1="3" id2="3" wcount="3" qtext="" ctext1="" ctext2="" photo1="" photo2="" video="Game_DisplayPlayer_Work_sucks_Scene1_a.mp4" />
<img id="3" type="auto" id1="28" id2="28" wcount="3" qtext="" ctext1="" ctext2="" photo1="" photo2="" video="Game_DisplayPlayer_Work_sucks_Scene3.mp4" />
<img id="4" type="auto" id1="5" id2="5" wcount="3" qtext="" ctext1="" ctext2="" photo1="" photo2="" video="Game_DisplayPlayer_Work_sucks_Scene1_b.mp4" />
<img id="5" resume="no" type="auto" stype="smenu" id1="9" id2="9" wcount="3" wcountb="5" wcounta="3" bid1="5" bid2="9" bid3="10" bid4="13" bid5="16" aid1="6" aid2="7" aid3="8" aid4="" bphoto1="1-1-100-133" bphoto2="1-2-100-133" bphoto3="1-3-100-133" bphoto4="1-4-100-133" bphoto5="1-5-100-133" aphoto1="1-1-a-100-133" aphoto2="1-1-b-100-133" aphoto3="1-1-c-100-133" aphoto4="" qtext="" ctext1="" ctext2="" photo1="" photo2="" video="Game_DisplayPlayer_Work_sucks_Scene1_1.mp4" />
<img id="6" type="auto" stype="smenu" id1="5" id2="5" wcount="3" wcountb="5" wcounta="3" bid1="5" bid2="9" bid3="10" bid4="13" bid5="16" aid1="6" aid2="7" aid3="8" aid4="" bphoto1="1-1-100-133" bphoto2="1-2-100-133" bphoto3="1-3-100-133" bphoto4="1-4-100-133" bphoto5="1-5-100-133" aphoto1="1-1-a-100-133" aphoto2="1-1-b-100-133" aphoto3="1-1-c-100-133" aphoto4="" qtext="" ctext1="" ctext2="" photo1="" photo2="" video="Game_DisplayPlayer_Work_sucks_Scene1_1_a.mp4" />
<img id="7" type="auto" stype="smenu" id1="5" id2="5" wcount="3" wcountb="5" wcounta="3" bid1="5" bid2="9" bid3="10" bid4="13" bid5="16" aid1="6" aid2="7" aid3="8" aid4="" bphoto1="1-1-100-133" bphoto2="1-2-100-133" bphoto3="1-3-100-133" bphoto4="1-4-100-133" bphoto5="1-5-100-133" aphoto1="1-1-a-100-133" aphoto2="1-1-b-100-133" aphoto3="1-1-c-100-133" aphoto4="" qtext="" ctext1="" ctext2="" photo1="" photo2="" video="Game_DisplayPlayer_Work_sucks_Scene1_1_b.mp4" />
<img id="8" type="auto" stype="smenu" id1="5" id2="5" wcount="3" wcountb="5" wcounta="3" bid1="5" bid2="9" bid3="10" bid4="13" bid5="16" aid1="6" aid2="7" aid3="8" aid4="" bphoto1="1-1-100-133" bphoto2="1-2-100-133" bphoto3="1-3-100-133" bphoto4="1-4-100-133" bphoto5="1-5-100-133" aphoto1="1-1-a-100-133" aphoto2="1-1-b-100-133" aphoto3="1-1-c-100-133" aphoto4="" qtext="" ctext1="" ctext2="" photo1="" photo2="" video="Game_DisplayPlayer_Work_sucks_Scene1_1_c.mp4" />
<img id="9" resume="no" type="auto" stype="smenu" id1="10" id2="10" wcount="3" wcountb="5" wcounta="" bid1="5" bid2="9" bid3="10" bid4="13" bid5="16" aid1="" aid2="" aid3="" aid4="" bphoto1="1-1-100-133" bphoto2="1-2-100-133" bphoto3="1-3-100-133" bphoto4="1-4-100-133" bphoto5="1-5-100-133" aphoto1="" aphoto2="" aphoto3="" aphoto4="" qtext="" ctext1="" ctext2="" photo1="" photo2="" video="Game_DisplayPlayer_Work_sucks_Scene1_2.mp4" />
<img id="10" resume="no" type="auto" stype="smenu" id1="13" id2="13" wcount="3" wcountb="5" wcounta="2" bid1="5" bid2="9" bid3="10" bid4="13" bid5="16" aid1="11" aid2="12" aid3="" aid4="" bphoto1="1-1-100-133" bphoto2="1-2-100-133" bphoto3="1-3-100-133" bphoto4="1-4-100-133" bphoto5="1-5-100-133" aphoto1="1-3-a-100-133" aphoto2="1-3-b-100-133" aphoto3="" aphoto4="" qtext="" ctext1="" ctext2="" photo1="" photo2="" video="Game_DisplayPlayer_Work_sucks_Scene1_3.mp4" />
<img id="11" type="auto" stype="smenu" id1="10" id2="10" wcount="3" wcountb="5" wcounta="2" bid1="5" bid2="9" bid3="10" bid4="13" bid5="16" aid1="11" aid2="12" aid3="" aid4="" bphoto1="1-1-100-133" bphoto2="1-2-100-133" bphoto3="1-3-100-133" bphoto4="1-4-100-133" bphoto5="1-5-100-133" aphoto1="1-3-a-100-133" aphoto2="1-3-b-100-133" aphoto3="" aphoto4="" qtext="" ctext1="" ctext2="" photo1="" photo2="" video="Game_DisplayPlayer_Work_sucks_Scene1_3_a.mp4" />
<img id="12" type="auto" stype="smenu" id1="10" id2="10" wcount="3" wcountb="5" wcounta="2" bid1="5" bid2="9" bid3="10" bid4="13" bid5="16" aid1="11" aid2="12" aid3="" aid4="" bphoto1="1-1-100-133" bphoto2="1-2-100-133" bphoto3="1-3-100-133" bphoto4="1-4-100-133" bphoto5="1-5-100-133" aphoto1="1-3-a-100-133" aphoto2="1-3-b-100-133" aphoto3="" aphoto4="" qtext="" ctext1="" ctext2="" photo1="" photo2="" video="Game_DisplayPlayer_Work_sucks_Scene1_3_b.mp4" />
<img id="13" resume="no" type="auto" stype="smenu" id1="16" id2="16" wcount="3" wcountb="5" wcounta="2" bid1="5" bid2="9" bid3="10" bid4="13" bid5="16" aid1="14" aid2="15" aid3="" aid4="" bphoto1="1-1-100-133" bphoto2="1-2-100-133" bphoto3="1-3-100-133" bphoto4="1-4-100-133" bphoto5="1-5-100-133" aphoto1="1-4-a-100-133" aphoto2="1-4-b-100-133" aphoto3="" aphoto4="" qtext="" ctext1="" ctext2="" photo1="" photo2="" video="Game_DisplayPlayer_Work_sucks_Scene1_4.mp4" />
<img id="14" type="auto" stype="smenu" id1="13" id2="13" wcount="3" wcountb="5" wcounta="2" bid1="5" bid2="9" bid3="10" bid4="13" bid5="16" aid1="14" aid2="15" aid3="" aid4="" bphoto1="1-1-100-133" bphoto2="1-2-100-133" bphoto3="1-3-100-133" bphoto4="1-4-100-133" bphoto5="1-5-100-133" aphoto1="1-4-a-100-133" aphoto2="1-4-b-100-133" aphoto3="" aphoto4="" qtext="" ctext1="" ctext2="" photo1="" photo2="" video="Game_DisplayPlayer_Work_sucks_Scene1_4_a.mp4" />
<img id="15" type="auto" stype="smenu" id1="13" id2="13" wcount="3" wcountb="5" wcounta="2" bid1="5" bid2="9" bid3="10" bid4="13" bid5="16" aid1="14" aid2="15" aid3="" aid4="" bphoto1="1-1-100-133" bphoto2="1-2-100-133" bphoto3="1-3-100-133" bphoto4="1-4-100-133" bphoto5="1-5-100-133" aphoto1="1-4-a-100-133" aphoto2="1-4-b-100-133" aphoto3="" aphoto4="" qtext="" ctext1="" ctext2="" photo1="" photo2="" video="Game_DisplayPlayer_Work_sucks_Scene1_4_b.mp4" />
<img id="16" resume="no" type="auto" stype="smenu" id1="17" id2="17" wcount="3" wcountb="5" wcounta="" bid1="5" bid2="9" bid3="10" bid4="13" bid5="16" aid1="" aid2="" aid3="" aid4="" bphoto1="1-1-100-133" bphoto2="1-2-100-133" bphoto3="1-3-100-133" bphoto4="1-4-100-133" bphoto5="1-5-100-133" aphoto1="" aphoto2="" aphoto3="" aphoto4="" qtext="" ctext1="" ctext2="" photo1="" photo2="" video="Game_DisplayPlayer_Work_sucks_Scene1_5.mp4" />
<img id="17" type="auto" id1="18" id2="18" wcount="3" qtext="" ctext1="" ctext2="" photo1="" photo2="" video="Game_DisplayPlayer_Work_sucks_Scene7.mp4" />
<img id="18" resume="no" type="auto" stype="smenu" id1="21" id2="21" wcount="3" wcountb="4" wcounta="2" bid1="18" bid2="21" bid3="24" bid4="26" aid1="19" aid2="20" aid3="" aid4="" bphoto1="7-1-100-133" bphoto2="7-2-100-133" bphoto3="7-3-100-133" bphoto4="7-4-100-133" aphoto1="7-1-a-100-133" aphoto2="7-1-b-100-133" aphoto3="" aphoto4="" qtext="" ctext1="" ctext2="" photo1="" photo2="" video="Game_DisplayPlayer_Work_sucks_Scene7_1.mp4" />
<img id="19" type="auto" stype="smenu" id1="18" id2="18" wcount="3" wcountb="4" wcounta="2" bid1="18" bid2="21" bid3="24" bid4="26" aid1="19" aid2="20" aid3="" aid4="" bphoto1="7-1-100-133" bphoto2="7-2-100-133" bphoto3="7-3-100-133" bphoto4="7-4-100-133" aphoto1="7-1-a-100-133" aphoto2="7-1-b-100-133" aphoto3="" aphoto4="" qtext="" ctext1="" ctext2="" photo1="" photo2="" video="Game_DisplayPlayer_Work_sucks_Scene7_1_a.mp4" />
<img id="20" type="auto" stype="smenu" id1="18" id2="18" wcount="3" wcountb="4" wcounta="2" bid1="18" bid2="21" bid3="24" bid4="26" aid1="19" aid2="20" aid3="" aid4="" bphoto1="7-1-100-133" bphoto2="7-2-100-133" bphoto3="7-3-100-133" bphoto4="7-4-100-133" aphoto1="7-1-a-100-133" aphoto2="7-1-b-100-133" aphoto3="" aphoto4="" qtext="" ctext1="" ctext2="" photo1="" photo2="" video="Game_DisplayPlayer_Work_sucks_Scene7_1_b.mp4" />
<img id="21" resume="no" type="auto" stype="smenu" id1="24" id2="24" wcount="3" wcountb="4" wcounta="2" bid1="18" bid2="21" bid3="24" bid4="26" aid1="22" aid2="23" aid3="" aid4="" bphoto1="7-1-100-133" bphoto2="7-2-100-133" bphoto3="7-3-100-133" bphoto4="7-4-100-133" aphoto1="7-2-a-100-133" aphoto2="7-2-b-100-133" aphoto3="" aphoto4="" qtext="" ctext1="" ctext2="" photo1="" photo2="" video="Game_DisplayPlayer_Work_sucks_Scene7_2.mp4" />
<img id="22" type="auto" stype="smenu" id1="21" id2="21" wcount="3" wcountb="4" wcounta="2" bid1="18" bid2="21" bid3="24" bid4="26" aid1="22" aid2="23" aid3="" aid4="" bphoto1="7-1-100-133" bphoto2="7-2-100-133" bphoto3="7-3-100-133" bphoto4="7-4-100-133" aphoto1="7-2-a-100-133" aphoto2="7-2-b-100-133" aphoto3="" aphoto4="" qtext="" ctext1="" ctext2="" photo1="" photo2="" video="Game_DisplayPlayer_Work_sucks_Scene7_2_a.mp4" />
<img id="23" type="auto" stype="smenu" id1="21" id2="21" wcount="3" wcountb="4" wcounta="2" bid1="18" bid2="21" bid3="24" bid4="26" aid1="22" aid2="23" aid3="" aid4="" bphoto1="7-1-100-133" bphoto2="7-2-100-133" bphoto3="7-3-100-133" bphoto4="7-4-100-133" aphoto1="7-2-a-100-133" aphoto2="7-2-b-100-133" aphoto3="" aphoto4="" qtext="" ctext1="" ctext2="" photo1="" photo2="" video="Game_DisplayPlayer_Work_sucks_Scene7_2_b.mp4" />
<img id="24" resume="no" type="auto" stype="smenu" id1="26" id2="26" wcount="3" wcountb="4" wcounta="1" bid1="18" bid2="21" bid3="24" bid4="26" aid1="25" aid2="" aid3="" aid4="" bphoto1="7-1-100-133" bphoto2="7-2-100-133" bphoto3="7-3-100-133" bphoto4="7-4-100-133" aphoto1="7-3-a-100-133" aphoto2="" aphoto3="" aphoto4="" qtext="" ctext1="" ctext2="" photo1="" photo2="" video="Game_DisplayPlayer_Work_sucks_Scene7_3.mp4" />
<img id="25" type="auto" stype="smenu" id1="24" id2="24" wcount="3" wcountb="4" wcounta="1" bid1="18" bid2="21" bid3="24" bid4="26" aid1="25" aid2="" aid3="" aid4="" bphoto1="7-1-100-133" bphoto2="7-2-100-133" bphoto3="7-3-100-133" bphoto4="7-4-100-133" aphoto1="7-3-a-100-133" aphoto2="" aphoto3="" aphoto4="" qtext="" ctext1="" ctext2="" photo1="" photo2="" video="Game_DisplayPlayer_Work_sucks_Scene7_3_a.mp4" />
<img id="26" resume="no" type="auto" stype="smenu" id1="27" id2="27" wcount="3" wcountb="4" wcounta="" bid1="18" bid2="21" bid3="24" bid4="26" aid1="" aid2="" aid3="" aid4="" bphoto1="7-1-100-133" bphoto2="7-2-100-133" bphoto3="7-3-100-133" bphoto4="7-4-100-133" aphoto1="" aphoto2="" aphoto3="" aphoto4="" qtext="" ctext1="" ctext2="" photo1="" photo2="" video="Game_DisplayPlayer_Work_sucks_Scene7_4.mp4" />
<img id="27" type="auto" id1="28" id2="28" wcount="3" qtext="" ctext1="" ctext2="" photo1="" photo2="" video="Game_DisplayPlayer_Work_sucks_Scene4.mp4" />
<img id="28" stype="smenu" id1="29" id2="30" wcount="3" wcounta="" wcountb="" qtext="OMG... she totally wants me...! Well mademoiselle, I'm all yours!" ctext1="Let me hold those gorgeous breasts of yours!" ctext2="Let me show you how hard I want you!" photo1="6-a" photo2="6-b" video="Game_DisplayPlayer_Work_sucks_Scene6.mp4" />
<img id="29" stype="smenu" id1="30" id2="34" wcount="3" wcounta="" wcountb="" qtext="I can't get enough of her...!" ctext1="Let me show you how hard I want you" ctext2="Let me have that tight pussy of yours!" photo1="6-b" photo2="6-3" video="Game_DisplayPlayer_Work_sucks_Scene6_1.mp4" />
<img id="30" resume="no" stype="smenu" id1="29" id2="34" wcount="3" wcountb="1" wcounta="3" bid1="30" bid2="" bid3="" bid4="" aid1="31" aid2="32" aid3="33" aid4="" bphoto1="6-2-100-133" bphoto2="" bphoto3="" bphoto4="" aphoto1="6-2-a-100-133" aphoto2="6-2-b-100-133" aphoto3="6-2-c-100-133" aphoto4="" qtext="I can't get enough of her...!" ctext1="Let me hold those gorgeous breasts of yours!" ctext2="Let me have that tight pussy of yours!" photo1="6-a" photo2="6-3" video="Game_DisplayPlayer_Work_sucks_Scene6_2.mp4" />
<img id="31" type="auto" stype="smenu" id1="30" id2="30" wcount="3" wcountb="1" wcounta="3" bid1="30" bid2="" bid3="" bid4="" aid1="31" aid2="32" aid3="33" aid4="" bphoto1="6-2-100-133" bphoto2="" bphoto3="" bphoto4="" aphoto1="6-2-a-100-133" aphoto2="6-2-b-100-133" aphoto3="6-2-c-100-133" aphoto4="" qtext="" ctext1="" ctext2="" photo1="" photo2="" video="Game_DisplayPlayer_Work_sucks_Scene6_2_a.mp4" />
<img id="32" type="auto" stype="smenu" id1="30" id2="30" wcount="3" wcountb="1" wcounta="3" bid1="30" bid2="" bid3="" bid4="" aid1="31" aid2="32" aid3="33" aid4="" bphoto1="6-2-100-133" bphoto2="" bphoto3="" bphoto4="" aphoto1="6-2-a-100-133" aphoto2="6-2-b-100-133" aphoto3="6-2-c-100-133" aphoto4="" qtext="" ctext1="" ctext2="" photo1="" photo2="" video="Game_DisplayPlayer_Work_sucks_Scene6_2_b.mp4" />
<img id="33" type="auto" stype="smenu" id1="30" id2="30" wcount="3" wcountb="1" wcounta="3" bid1="30" bid2="" bid3="" bid4="" aid1="31" aid2="32" aid3="33" aid4="" bphoto1="6-2-100-133" bphoto2="" bphoto3="" bphoto4="" aphoto1="6-2-a-100-133" aphoto2="6-2-b-100-133" aphoto3="6-2-c-100-133" aphoto4="" qtext="" ctext1="" ctext2="" photo1="" photo2="" video="Game_DisplayPlayer_Work_sucks_Scene6_2_c.mp4" />
<img id="34" resume="no" type="auto" stype="smenu" id1="38" id2="38" wcount="3" wcountb="1" wcounta="3" bid1="34" bid2="" bid3="" bid4="" aid1="35" aid2="36" aid3="37" aid4="" bphoto1="6-3-100-133" bphoto2="" bphoto3="" bphoto4="" aphoto1="6-3-a-100-133" aphoto2="6-3-b-100-133" aphoto3="6-3-c-100-133" aphoto4="" qtext="" ctext1="" ctext2="" photo1="" photo2="" video="Game_DisplayPlayer_Work_sucks_Scene6_3.mp4" />
<img id="35" type="auto" stype="smenu" id1="34" id2="34" wcount="3" wcountb="1" wcounta="3" bid1="34" bid2="" bid3="" bid4="" aid1="35" aid2="36" aid3="37" aid4="" bphoto1="6-3-100-133" bphoto2="" bphoto3="" bphoto4="" aphoto1="6-3-a-100-133" aphoto2="6-3-b-100-133" aphoto3="6-3-c-100-133" aphoto4="" qtext="" ctext1="" ctext2="" photo1="" photo2="" video="Game_DisplayPlayer_Work_sucks_Scene6_3_a.mp4" />
<img id="36" type="auto" stype="smenu" id1="34" id2="34" wcount="3" wcountb="1" wcounta="3" bid1="34" bid2="" bid3="" bid4="" aid1="35" aid2="36" aid3="37" aid4="" bphoto1="6-3-100-133" bphoto2="" bphoto3="" bphoto4="" aphoto1="6-3-a-100-133" aphoto2="6-3-b-100-133" aphoto3="6-3-c-100-133" aphoto4="" qtext="" ctext1="" ctext2="" photo1="" photo2="" video="Game_DisplayPlayer_Work_sucks_Scene6_3_b.mp4" />
<img id="37" type="auto" stype="smenu" id1="34" id2="34" wcount="3" wcountb="1" wcounta="3" bid1="34" bid2="" bid3="" bid4="" aid1="35" aid2="36" aid3="37" aid4="" bphoto1="6-3-100-133" bphoto2="" bphoto3="" bphoto4="" aphoto1="6-3-a-100-133" aphoto2="6-3-b-100-133" aphoto3="6-3-c-100-133" aphoto4="" qtext="" ctext1="" ctext2="" photo1="" photo2="" video="Game_DisplayPlayer_Work_sucks_Scene6_3_c.mp4" />
<img id="38" type="auto" id1="39" id2="39" wcount="3" qtext="" ctext1="" ctext2="" photo1="" photo2="" video="Game_DisplayPlayer_Work_sucks_Scene6_4.mp4" />
<img id="39" type="win" />
<img id="40" stype="smenu" id1="41" id2="42" wcount="3" wcounta="" wcountb="" qtext="Calm down... don't look at that ass... Gosh! How could one not touch it?" ctext1="Ahh... I can't hold myseld back, I want to touch it!" ctext2="No... so hard. Keep calm! Don't touch it!" photo1="2-a" photo2="2-b" video="Game_DisplayPlayer_Work_sucks_Scene2.mp4" />
<img id="41" type="auto" id1="3" id2="3" wcount="3" qtext="" ctext1="" ctext2="" photo1="" photo2="" video="Game_DisplayPlayer_Work_sucks_Scene2_a.mp4" />
<img id="42" type="auto" id1="43" id2="43" wcount="3" qtext="" ctext1="" ctext2="" photo1="" photo2="" video="Game_DisplayPlayer_Work_sucks_Scene2_b.mp4" />
<img id="43" type="auto" id1="28" id2="28" wcount="3" qtext="" ctext1="" ctext2="" photo1="" photo2="" video="Game_DisplayPlayer_Work_sucks_Scene5.mp4" />